atoma/__init__.py
atoma/atom.py
atoma/const.py
atoma/exceptions.py
atoma/json_feed.py
atoma/opml.py
atoma/rss.py
atoma/simple.py
atoma/utils.py
atoma-0.0.17.dist-info/LICENSE
atoma-0.0.17.dist-info/METADATA
atoma-0.0.17.dist-info/WHEEL
atoma-0.0.17.dist-info/top_level.txt
atoma-0.0.17.dist-info/RECORD
