Metadata-Version: 2.1
Name: atoma
Version: 0.0.17
Summary: Atom, RSS and JSON feed parser for Python 3
Home-page: https://github.com/NicolasLM/atoma
Author: Nicolas Le Manchet
Author-email: nicolas@lemanchet.fr
License: MIT
Keywords: atom rss json feed feeds syndication parser RFC4287
Platform: UNKNOWN
Classifier: Development Status :: 4 - Beta
Classifier: Intended Audience :: Developers
Classifier: Topic :: Software Development :: Libraries
Classifier: License :: OSI Approved :: MIT License
Classifier: Natural Language :: English
Classifier: Programming Language :: Python :: 3
Classifier: Programming Language :: Python :: 3 :: Only
Classifier: Programming Language :: Python :: 3.6
Classifier: Programming Language :: Python :: 3.7
Classifier: Topic :: Text Processing :: Markup :: XML
Provides-Extra: tests
